fhirstore/__init__.py
fhirstore/fhirstore.py
fhirstore/utils.py
fhirstore/schema/__init__.py
fhirstore/schema/fhir.schema.json
fhirstore/schema/parser.py
fhirstore/search/__init__.py
fhirstore/search/bundle.py
fhirstore/search/corequerybuilder.py
fhirstore/search/searcharguments.py
fhirstore-0.4.8.dist-info/LICENSE
fhirstore-0.4.8.dist-info/METADATA
fhirstore-0.4.8.dist-info/WHEEL
fhirstore-0.4.8.dist-info/top_level.txt
fhirstore-0.4.8.dist-info/RECORD
