Metadata-Version: 2.1
Name: fhirstore
Version: 0.4.8
Summary: Manipulating FHIR data leveraging MongoDB as storage layer
Home-page: https://github.com/arkhn/pyfhirstore/
Author: Arkhn
Author-email: contact@arkhn.org
License: UNKNOWN
Platform: UNKNOWN
Classifier: Programming Language :: Python :: 3
Classifier: License :: OSI Approved :: Apache Software License
Classifier: Operating System :: OS Independent
Requires-Python: >=3.6
Requires-Dist: dotty-dict (==1.2.1)
Requires-Dist: elasticsearch (==7.0.5)
Requires-Dist: jsonschema (==3.0.2)
Requires-Dist: pymongo (==3.9.0)
Requires-Dist: tqdm (==4.36.1)
